llama_index/tools/neo4j/__init__.py
llama_index/tools/neo4j/base.py
llama_index/tools/neo4j/query_validator.py
llama_index_tools_neo4j-0.4.1.dist-info/METADATA
llama_index_tools_neo4j-0.4.1.dist-info/WHEEL
llama_index_tools_neo4j-0.4.1.dist-info/licenses/LICENSE
llama_index_tools_neo4j-0.4.1.dist-info/RECORD
