Metadata-Version: 2.4
Name: llama-index-tools-neo4j
Version: 0.4.1
Summary: llama-index tools neo4j integration
Author-email: Your Name <you@example.com>
Maintainer: shahafp
License-Expression: MIT
License-File: LICENSE
Keywords: cypher,graph,neo4j
Requires-Python: <4.0,>=3.9
Requires-Dist: llama-index-core<0.15,>=0.13.0
Requires-Dist: llama-index-graph-stores-neo4j<0.6,>=0.5.0
